README.rst
setup.py
pluginloader/__init__.py
pluginloader.egg-info/PKG-INFO
pluginloader.egg-info/SOURCES.txt
pluginloader.egg-info/dependency_links.txt
pluginloader.egg-info/not-zip-safe
pluginloader.egg-info/top_level.txt