Metadata-Version: 1.1
Name: pluginloader
Version: 0.1.3
Summary: Library to manage plugins/extensions in your applications.
Home-page: https://github.com/magmax/python-pluginloader
Author: Miguel Ángel García
Author-email: miguelangel.garcia@gmail.com
License: MIT
Keywords: plugin,plugins,extension,extensions,engine,loader
Platform: UNKNOWN
Classifier: Development Status :: 4 - Beta
Classifier: Environment :: Console
Classifier: Intended Audience :: Developers
Classifier: License :: OSI Approved :: MIT License
Classifier: Operating System :: OS Independent
